oktoberfest/__init__.py
oktoberfest/__main__.py
oktoberfest/data/__init__.py
oktoberfest/data/spectra.py
oktoberfest/plotting/__init__.py
oktoberfest/plotting/plotting.py
oktoberfest/predict/__init__.py
oktoberfest/predict/alignment.py
oktoberfest/predict/dlomix.py
oktoberfest/predict/koina.py
oktoberfest/predict/predictor.py
oktoberfest/predict/utils.py
oktoberfest/preprocessing/__init__.py
oktoberfest/preprocessing/preprocessing.py
oktoberfest/rescore/__init__.py
oktoberfest/rescore/rescore.py
oktoberfest/runner.py
oktoberfest/utils/__init__.py
oktoberfest/utils/config.py
oktoberfest/utils/example_configs.py
oktoberfest/utils/groupiterator.py
oktoberfest/utils/logging.py
oktoberfest/utils/multiprocessing_pool.py
oktoberfest/utils/process_step.py
oktoberfest/utils/quantification.py
oktoberfest-0.10.0.dist-info/LICENSE
oktoberfest-0.10.0.dist-info/METADATA
oktoberfest-0.10.0.dist-info/WHEEL
oktoberfest-0.10.0.dist-info/entry_points.txt
oktoberfest-0.10.0.dist-info/RECORD
