Metadata-Version: 2.3
Name: oktoberfest
Version: 0.10.0
Summary: Public repo oktoberfest
License: MIT
Author: Wilhelmlab at Technical University of Munich
Requires-Python: >=3.10.0,<3.13.0
Classifier: License :: OSI Approved :: MIT License
Classifier: Programming Language :: Python :: 3
Classifier: Programming Language :: Python :: 3.10
Classifier: Programming Language :: Python :: 3.11
Classifier: Programming Language :: Python :: 3.12
Requires-Dist: PyYAML (>=5.4.1)
Requires-Dist: anndata (>=0.10.5post1,<0.11.0)
Requires-Dist: array-api-compat (==1.12.0)
Requires-Dist: click (>=8.0.0)
Requires-Dist: koinapy (>=0.0.7,<0.0.11)
Requires-Dist: matplotlib (>=3.6.3,<4.0.0)
Requires-Dist: mokapot (>=0.9.1,<0.11.0)
Requires-Dist: numpy (>=1.26.4)
Requires-Dist: picked_group_fdr (>=0.9.0)
Requires-Dist: rich (>=10.3.0)
Requires-Dist: seaborn (>=0.12.2,<0.14.0)
Requires-Dist: spectrum-fundamentals (>=0.9.0,<0.10.0)
Requires-Dist: spectrum-io (>=0.8.0,<0.9.0)
Requires-Dist: spectrum-utils (>=0.4.2,<0.5.0)
Project-URL: Documentation, https://oktoberfest.readthedocs.io
Project-URL: Homepage, https://github.com/wilhelm-lab/oktoberfest
Project-URL: Repository, https://github.com/wilhelm-lab/oktoberfest
